smg_mcp/__init__.py
smg_mcp-0.0.1.dist-info/METADATA
smg_mcp-0.0.1.dist-info/WHEEL
smg_mcp-0.0.1.dist-info/top_level.txt
smg_mcp-0.0.1.dist-info/RECORD
