Metadata-Version: 2.4
Name: smg-mcp
Version: 0.0.1
Summary: Model Context Protocol (MCP) implementation for Shepherd Model Gateway
Author: Shepherd Team
License: Apache-2.0
Project-URL: Homepage, https://github.com/shepherd-ai/shepherd
Keywords: llm,inference,ml,ai
Classifier: Development Status :: 1 - Planning
Classifier: Intended Audience :: Developers
Classifier: License :: OSI Approved :: Apache Software License
Classifier: Programming Language :: Python :: 3
Classifier: Programming Language :: Rust
Requires-Python: >=3.8
